Metadata-Version: 2.1
Name: FeatureImportance
Version: 0.0.3
Summary: A  library to compute feature importance for voting classifiers in the ensembled voting
Home-page: 
Author: Panashe H Guzha
Author-email: panasheguzha21@gmail.com
License: MIT
Keywords: feature importance
Classifier: Development Status :: 5 - Production/Stable
Classifier: Intended Audience :: Education
Classifier: Operating System :: Microsoft :: Windows :: Windows 10
Classifier: License :: OSI Approved :: MIT License
Classifier: Programming Language :: Python :: 3
License-File: LICENCE.txt
